decimal_binary_converter/__init__.py
decimal_binary_converter/converter.py
simple_example_package_of_decimal_binary_converter-0.0.1.dist-info/licenses/LICENSE
simple_example_package_of_decimal_binary_converter-0.0.1.dist-info/METADATA
simple_example_package_of_decimal_binary_converter-0.0.1.dist-info/WHEEL
simple_example_package_of_decimal_binary_converter-0.0.1.dist-info/top_level.txt
simple_example_package_of_decimal_binary_converter-0.0.1.dist-info/RECORD
