Metadata-Version: 2.4
Name: simple_example_package_of_decimal_binary_converter
Version: 0.0.1
Summary: Package for converting decimal numbers into binary numbers
Author-email: Example Author <author@example.com>
License: MIT License
Project-URL: Homepage, https://github.com/MunchProductionz/decimal-binary-converter
Classifier: Programming Language :: Python :: 3
Classifier: Operating System :: OS Independent
Classifier: License :: OSI Approved :: MIT License
Requires-Python: >=3.8
License-File: LICENSE
Dynamic: license-file
